schematized_jwt/__init__.py
schematized_jwt/annotations.py
schematized_jwt/decoders.py
schematized_jwt/encoders.py
schematized_jwt/enums.py
schematized_jwt/exceptions.py
schematized_jwt/extenders.py
schematized_jwt/main.py
schematized_jwt/validators.py
schematized_jwt-0.1.0.dist-info/METADATA
schematized_jwt-0.1.0.dist-info/WHEEL
schematized_jwt-0.1.0.dist-info/entry_points.txt
schematized_jwt-0.1.0.dist-info/RECORD
