Metadata-Version: 2.4
Name: schematized-jwt
Version: 0.1.0
Summary: A project for encoding and decoding JWT tokens using Pydantic schemas.
Author-email: Vladimir Boltushev <vladimirboltushev@yandex.ru>
Requires-Python: >=3.12
Requires-Dist: pydantic>=2.11.7
Requires-Dist: pyjwt>=2.10.1
